agit/config.py
agit/grammar.py
agit/logger.py
agit/main.py
agit/openai_api.py
agit/os_iface.py
agit/rag.py
agit/security.py
agit/selfdocument.py
agit/util.py
microagi_git-0.0.6.dist-info/LICENSE.txt
microagi_git-0.0.6.dist-info/METADATA
microagi_git-0.0.6.dist-info/WHEEL
microagi_git-0.0.6.dist-info/entry_points.txt
microagi_git-0.0.6.dist-info/RECORD
